xolir/__init__.py
xolir/build_hook.py
xolir-0.0.1.dist-info/METADATA
xolir-0.0.1.dist-info/WHEEL
xolir-0.0.1.dist-info/top_level.txt
xolir-0.0.1.dist-info/RECORD
