Metadata-Version: 2.4
Name: xolir
Version: 0.0.1
Summary: Python protobuf classes for Tel IR api
Author-email: Mark Verleg <mverleg.noreply@gmail.com>
Project-URL: Homepage, https://github.com/mverleg/xolir
Project-URL: Issues, https://github.com/mverleg/xolir/issues
Classifier: Programming Language :: Python :: 3
Classifier: Operating System :: OS Independent
Requires-Python: >=3.8
Requires-Dist: grpcio
